cogstack_model_gateway_client/__init__.py
cogstack_model_gateway_client/client.py
cogstack_model_gateway_client/exceptions.py
cogstack_model_gateway_client-0.1.10.dist-info/METADATA
cogstack_model_gateway_client-0.1.10.dist-info/WHEEL
cogstack_model_gateway_client-0.1.10.dist-info/licenses/LICENSE
cogstack_model_gateway_client-0.1.10.dist-info/RECORD
