Metadata-Version: 2.4
Name: cogstack-model-gateway-client
Version: 0.1.10
Summary: A Python client for the CogStack Model Gateway
License: Apache-2.0
License-File: LICENSE
Author: Phoevos Kalemkeris
Author-email: phoevos.kalemkeris@ucl.ac.uk
Requires-Python: >=3.10
Classifier: Programming Language :: Python :: 3
Classifier: Programming Language :: Python :: 3.10
Classifier: Programming Language :: Python :: 3.11
Classifier: Programming Language :: Python :: 3.12
Classifier: Programming Language :: Python :: 3.13
Classifier: Intended Audience :: Developers
Requires-Dist: httpx (>=0.28.1,<0.29.0)
Requires-Dist: tenacity (>=9.1.2,<10.0.0)
Project-URL: Bug Tracker, https://github.com/CogStack/cogstack-model-gateway/issues
Project-URL: Documentation, https://github.com/CogStack/cogstack-model-gateway/tree/main/client/README.md
Project-URL: Homepage, https://github.com/CogStack/cogstack-model-gateway
Project-URL: Repository, https://github.com/CogStack/cogstack-model-gateway
